FineTune_Uunsloth_Mistral_7b/__init__.py
FineTune_Uunsloth_Mistral_7b/fine_tune.py
FineTune_Uunsloth_Mistral_7b-0.1.10.dist-info/LICENSE
FineTune_Uunsloth_Mistral_7b-0.1.10.dist-info/METADATA
FineTune_Uunsloth_Mistral_7b-0.1.10.dist-info/WHEEL
FineTune_Uunsloth_Mistral_7b-0.1.10.dist-info/entry_points.txt
FineTune_Uunsloth_Mistral_7b-0.1.10.dist-info/top_level.txt
FineTune_Uunsloth_Mistral_7b-0.1.10.dist-info/RECORD
