Metadata-Version: 2.1
Name: FineTune-Uunsloth-Mistral-7b
Version: 0.1.10
Summary: A package for fine-tuning Mistral model and generating responses.
Author: Mehrdad Almasi and Demival VASQUES FILHO
Author-email: Mehrdad.al.2023@gmail.com, demival.vasques@uni.lu 
Classifier: Programming Language :: Python :: 3
Classifier: License :: OSI Approved :: MIT License
Classifier: Operating System :: OS Independent
Requires-Python: >=3.6
License-File: LICENSE
Requires-Dist: datasets (>=1.6.0)
Requires-Dist: transformers (>=4.6.0)
Requires-Dist: pandas (>=1.1.0)
Requires-Dist: peft
Requires-Dist: trl
Requires-Dist: bitsandbytes (>=0.26.0)
